EnigmaShield/CryptoBloom.py
EnigmaShield/CryptoTypes.py
EnigmaShield/DataSet.py
EnigmaShield/__init__.py
EnigmaShield-0.0.1.dist-info/METADATA
EnigmaShield-0.0.1.dist-info/WHEEL
EnigmaShield-0.0.1.dist-info/top_level.txt
EnigmaShield-0.0.1.dist-info/RECORD
