Metadata-Version: 2.1
Name: EnigmaShield
Version: 0.0.1
Summary: The "Module Encryption Toolkit" is a powerful Python module designed to enhance the security of your code by encrypting the entire process, including runtime values. With this toolkit, you can safeguard sensitive data and effectively prevent reverse engineering attempts.
Author: NagiPragalathan N
Author-email: <nagipragalathan@gmail.com>
Keywords: python,cryptography,encryption,decryption,security,Cryptosystem,Cipher,Key,Key management,Key exchange,Public key cryptography,Symmetric key cryptography,Asymmetric key cryptography,Hash function,Digital signatures,Secure communication,Authentication,Confidentiality,Integrity,Non-repudiation,Cryptanalysis
Classifier: Development Status :: 1 - Planning
Classifier: Intended Audience :: Developers
Classifier: Programming Language :: Python :: 3
Classifier: Operating System :: Unix
Classifier: Operating System :: MacOS :: MacOS X
Classifier: Operating System :: Microsoft :: Windows
